{
  "resourceType": "Observation",
  "id": "ObservationExample",
  "status": "final",
  "derivedFrom": [
    {
      "reference": "QuestionnaireResponse/QuestionnareResponseExample"
    }
  ],
  "code": {
    "coding": [
      {
        "code": "405049007",
        "system": "http://snomed.info/sct",
        "display": "Level of depression (observable entity)"
      }
    ]
  },
  "valueCodeableConcept": {
    "coding": [
      {
        "code": "162470006",
        "system": "http://snomed.info/sct",
        "display": "Symptom severe (finding)"
      }
    ]
  },
  "focus": [
    {
      "reference": "Condition/ConditionExample"
    }
  ],
  "_effectiveDateTime": {
    "extension": [
      {
        "url": "http://hl7.eu/fhir/extensions/StructureDefinition/periods-of-life",
        "valueCodeableConcept": {
          "coding": [
            {
              "code": "713152004",
              "system": "http://snomed.info/sct",
              "display": "Early childhood"
            }
          ]
        }
      }
    ]
  }
}
